Workbook

Sheet Summary
B2: VERTIV HOLDINGS (VRT)
B3: $ in millions, fiscal years ending Dec 31, shaded columns are forecasts
B5: Key Outputs | C5: 2023A | D5: 2024A | E5: 2025A | F5: 2026E | G5: 2027E | H5: 2028E | I5: 2029E
B6: Net Sales | C6: =Model!C16 -> 6863.2 | D6: =Model!D16 -> 8011.8 | E6: =Model!E16 -> 10229.9 | F6: =Model!F16 -> 13605.767 | G6: =Model!G16 -> 17551.439 | H6: =Model!H16 -> 21412.756 | I6: =Model!I16 -> 25052.925
B7: Sales Growth | D7: =D6/C6-1 -> 0.16735634 | E7: =E6/D6-1 -> 0.27685414 | F7: =F6/E6-1 -> 0.33 | G7: =G6/F6-1 -> 0.29 | H7: =H6/G6-1 -> 0.22 | I7: =I6/H6-1 -> 0.17
B8: Gross Margin | C8: =Model!C22/Model!C16 -> 0.34976396 | D8: =Model!D22/Model!D16 -> 0.3662348 | E8: =Model!E22/Model!E16 -> 0.36317071 | F8: =Model!F22/Model!F16 -> 0.36 | G8: =Model!G22/Model!G16 -> 0.36 | H8: =Model!H22/Model!H16 -> 0.36 | I8: =Model!I22/Model!I16 -> 0.36
B9: Opearating Profit | C9: =Model!C29 -> 872.2 | D9: =Model!D29 -> 1367.4 | E9: =Model!E29 -> 1829.7 | F9: =Model!F29 -> 2511.2822 | G9: =Model!G29 -> 3467.3023 | H9: =Model!H29 -> 4397.6426 | I9: =Model!I29 -> 5356.9434
B10: Opearting Margin | C10: =C9/C6 -> 0.12708358 | D10: =D9/D6 -> 0.17067326 | E10: =E9/E6 -> 0.17885805 | F10: =F9/F6 -> 0.18457484 | G10: =G9/G6 -> 0.19755088 | H10: =H9/H6 -> 0.2053749 | I10: =I9/I6 -> 0.21382507
B11: Net Income | C11: =Model!C38 -> 460.2 | D11: =Model!D38 -> 495.8 | E11: =Model!E38 -> 1332.8 | F11: =Model!F38 -> 1805.625 | G11: =Model!G38 -> 2537.812 | H11: =Model!H38 -> 3250.3541 | I11: =Model!I38 -> 3985.0509
B12: Net Margin | C12: =C11/C6 -> 0.06705327 | D12: =D11/D6 -> 0.061883722 | E12: =E11/E6 -> 0.13028475 | F12: =F11/F6 -> 0.13271027 | G12: =G11/G6 -> 0.14459282 | H12: =H11/H6 -> 0.15179522 | I12: =I11/I6 -> 0.1590653
B13: Operating Cash flow | C13: =Model!C112 -> 900.5 | D13: =Model!D112 -> 1319.3 | E13: =Model!E112 -> 2113.8 | F13: =Model!F112 -> 2592.601 | G13: =Model!G112 -> 2505.3321 | H13: =Model!H112 -> 3209.2658 | I13: =Model!I112 -> 4089.9432
B14: Capital Expenditures | C14: =Model!C115 -> -127.9 | D14: =Model!D115 -> -167 | E14: =Model!E115 -> -220 | F14: =Model!F115 -> -476.20185 | G14: =Model!G115 -> -526.54318 | H14: =Model!H115 -> -535.3189 | I14: =Model!I115 -> -501.05849
B15: Free Cash Flow (OCF + CAPEX) | C15: =SUM(C13:C14) -> 772.6 | D15: =SUM(D13:D14) -> 1152.3 | E15: =SUM(E13:E14) -> 1893.8 | F15: =SUM(F13:F14) -> 2116.3992 | G15: =SUM(G13:G14) -> 1978.789 | H15: =SUM(H13:H14) -> 2673.9469 | I15: =SUM(I13:I14) -> 3588.8847
B16: Cash and Cash Equivalents (B/s) | C16: =Model!C46 -> 780.4 | D16: =Model!D46 -> 1227.6 | E16: =Model!E46 -> 1728.4 | F16: =Model!F46 -> 3426.7179 | G16: =Model!G46 -> 5257.7163 | H16: =Model!H46 -> 7748.2455 | I16: =Model!I46 -> 11116.978
B17: Total Debt | C17: =Model!C70+Model!C78 -> 2940.9 | D17: =Model!D70+Model!D78 -> 2928.2 | E17: =Model!E70+Model!E78 -> 2913 | F17: =Model!F70+Model!F78 -> 2892.1 | G17: =Model!G70+Model!G78 -> 2871.2 | H17: =Model!H70+Model!H78 -> 2850.3 | I17: =Model!I70+Model!I78 -> 2829.4
B18: Net Cash / (Net Debt) | C18: =Model!C46+Model!C47-Model!C70-Model!C78 -> -2160.5 | D18: =Model!D46+Model!D47-Model!D70-Model!D78 -> -1700.6 | E18: =Model!E46+Model!E47-Model!E70-Model!E78 -> -1085.1 | F18: =Model!F46+Model!F47-Model!F70-Model!F78 -> 634.11792 | G18: =Model!G46+Model!G47-Model!G70-Model!G78 -> 2486.0163 | H18: =Model!H46+Model!H47-Model!H70-Model!H78 -> 4997.4455 | I18: =Model!I46+Model!I47-Model!I70-Model!I78 -> 8387.0776

Sheet Model
B2: VERTIV HOLDINGS (VRT)
B3: 3 Statement Projection Model
B5: Key
B6: Blue Text | C6: Historical data/Input/Assumption
B7: Black Text | C7: Formulas/Calculation
B9: INCOME STATEMENT
B10: $ in millions, fiscal years ending Dec 31
C12: 2023A | D12: 2024A | E12: 2025A | F12: 2026E | G12: 2027E | H12: 2028E | I12: 2029E
B13: Net sales
B14: Net sales - Products | C14: 5406.1 | D14: 6393.5 | E14: 8390.6
B15: Net sales - Services | C15: 1457.1 | D15: 1618.3 | E15: 1839.3
B16: Total Net sales | C16: =SUM(C14:C15) -> 6863.2 | D16: =SUM(D14:D15) -> 8011.8 | E16: =SUM(E14:E15) -> 10229.9 | F16: =E16*(1+F196) -> 13605.767 | G16: =F16*(1+G196) -> 17551.439 | H16: =G16*(1+H196) -> 21412.756 | I16: =H16*(1+I196) -> 25052.925
B18: Cost of Sales
B19: COS - Products | C19: 3575.7 | D19: 4099.4 | E19: 5447.2
B20: COS - Services | C20: 887 | D20: 978.2 | E20: 1067.5
B21: Total Cost of Sales | C21: =SUM(C19:C20) -> 4462.7 | D21: =SUM(D19:D20) -> 5077.6 | E21: =SUM(E19:E20) -> 6514.7 | F21: =F16-F22 -> 8707.6909 | G21: =G16-G22 -> 11232.921 | H21: =H16-H22 -> 13704.164 | I21: =I16-I22 -> 16033.872
B22: Gross Profit | C22: =C16-C21 -> 2400.5 | D22: =D16-D21 -> 2934.2 | E22: =E16-E21 -> 3715.2 | F22: =F16*F199 -> 4898.0761 | G22: =G16*G199 -> 6318.5182 | H22: =H16*H199 -> 7708.5922 | I22: =I16*I199 -> 9019.0529
B24: Operating Costs
B25: SGA | C25: 1312.3 | D25: 1374 | E25: 1617.8 | F25: =F16*F202 -> 2040.865 | G25: =G16*G202 -> 2544.9587 | H25: =H16*H202 -> 2997.7859 | I25: =I16*I202 -> 3382.1448
B26: Amortization of intangibles | C26: 181.3 | D26: 184.2 | E26: 200.4 | F26: 277.9 | G26: 218.5 | H26: 206.1 | I26: 154.7
B27: Other Operating expenses | C27: 34.7 | D27: 8.6 | E27: 67.3 | F27: =F16*F207 -> 68.028835 | G27: =G16*G207 -> 87.757197 | H27: =H16*H207 -> 107.06378 | I27: =I16*I207 -> 125.26462
B28: Total Operating Costs | C28: =SUM(C25:C27) -> 1528.3 | D28: =SUM(D25:D27) -> 1566.8 | E28: =SUM(E25:E27) -> 1885.5 | F28: =SUM(F25:F27) -> 2386.7939 | G28: =SUM(G25:G27) -> 2851.2159 | H28: =SUM(H25:H27) -> 3310.9496 | I28: =SUM(I25:I27) -> 3662.1094
B29: Operating Profit | C29: =C22-C28 -> 872.2 | D29: =D22-D28 -> 1367.4 | E29: =E22-E28 -> 1829.7 | F29: =F22-F28 -> 2511.2822 | G29: =G22-G28 -> 3467.3023 | H29: =H22-H28 -> 4397.6426 | I29: =I22-I28 -> 5356.9434
B31: Non Operating Expenses
B32: Interest expense, net | C32: 180.1 | D32: 150.4 | E32: 86.1 | F32: =F246 -> 150.98811 | G32: =G246 -> 149.90091 | H32: =H246 -> 148.81371 | I32: =I246 -> 147.72651
B33: Loss on extinguishment of debt | C33: 0.5 | D33: 2.4 | E33: 1.7 | F33: 0 | G33: 0 | H33: 0 | I33: 0
B34: Change in fair value of warrant liabilities | C34: 157.9 | D34: 449.2 | E34: 0 | F34: 0 | G34: 0 | H34: 0 | I34: 0
B35: Total non operating expenses | C35: =SUM(C32:C34) -> 338.5 | D35: =SUM(D32:D34) -> 602 | E35: =SUM(E32:E34) -> 87.8 | F35: =SUM(F32:F34) -> 150.98811 | G35: =SUM(G32:G34) -> 149.90091 | H35: =SUM(H32:H34) -> 148.81371 | I35: =SUM(I32:I34) -> 147.72651
B36: Earnings Before Tax | C36: =C29-C35 -> 533.7 | D36: =D29-D35 -> 765.4 | E36: =E29-E35 -> 1741.9 | F36: =F29-F35 -> 2360.2941 | G36: =G29-G35 -> 3317.4014 | H36: =H29-H35 -> 4248.8289 | I36: =I29-I35 -> 5209.2169
B37: Income tax expense | C37: 73.5 | D37: 269.6 | E37: 409.1 | F37: =F36*F213 -> 554.66912 | G37: =G36*G213 -> 779.58932 | H37: =H36*H213 -> 998.47478 | I37: =I36*I213 -> 1224.166
B38: Net Income/(Loss) | C38: =C36-C37 -> 460.2 | D38: =D36-D37 -> 495.8 | E38: =E36-E37 -> 1332.8 | F38: =F36-F37 -> 1805.625 | G38: =G36-G37 -> 2537.812 | H38: =H36-H37 -> 3250.3541 | I38: =I36-I37 -> 3985.0509
B41: BALANCE SHEET
B43: ASSETS:
B45: Current Assets
B46: Cash and cash equivalents | C46: 780.4 | D46: 1227.6 | E46: 1728.4 | F46: =F151-$E$152 -> 3426.7179 | G46: =G151-$E$152 -> 5257.7163 | H46: =H151-$E$152 -> 7748.2455 | I46: =I151-$E$152 -> 11116.978
B47: Short-term investments | D47: 0 | E47: 99.5 | F47: =E47 -> 99.5 | G47: =F47 -> 99.5 | H47: =G47 -> 99.5 | I47: =H47 -> 99.5
B48: Accounts receivable | C48: 2118.1 | D48: 2362.7 | E48: 3109 | F48: =F256 -> 4100.3681 | G48: =G256 -> 5289.4749 | H48: =H256 -> 6453.1594 | I48: =I256 -> 7550.1965
B49: Inventories | C49: 884.3 | D49: 1244.4 | E49: 1456.5 | F49: =F257 -> 2385.6687 | G49: =G257 -> 2769.7614 | H49: =H257 -> 3191.3806 | I49: =I257 -> 3514.2733
B50: Other current assets | C50: 218.7 | D50: 267.1 | E50: 426.1 | F50: =F258 -> 530.62491 | G50: =G258 -> 684.50614 | H50: =H258 -> 835.09749 | I50: =I258 -> 977.06406
B51: Total Current Assets | C51: =SUM(C46:C50) -> 4001.5 | D51: =SUM(D46:D50) -> 5101.8 | E51: =SUM(E46:E50) -> 6819.5 | F51: =SUM(F46:F50) -> 10542.88 | G51: =SUM(G46:G50) -> 14100.959 | H51: =SUM(H46:H50) -> 18327.383 | I51: =SUM(I46:I50) -> 23258.011
B53: Non - Current Assets
B54: Property, plant and equipment, net | C54: 560.1 | D54: 625.1 | E54: 921.8 | F54: =F222 -> 1259.7318 | G54: =G222 -> 1597.3153 | H54: =H222 -> 1893.0369 | I54: =I222 -> 2110.1398
B56: Other Assets
B57: Goodwill | C57: 1330.3 | D57: 1321.1 | E57: 2033.7 | F57: =F238 -> 2283.3 | G57: =G238 -> 2283.3 | H57: =H238 -> 2283.3 | I57: =I238 -> 2283.3
B58: Other intangible assets, net | C58: 1672.9 | D58: 1487.1 | E58: 1894.8 | F58: =F236 -> 1674.2 | G58: =G236 -> 1455.7 | H58: =H236 -> 1249.6 | I58: =I236 -> 1094.9
B59: Deferred income taxes | C59: 159.8 | D59: 303.3 | E59: 179.6 | F59: =E59 -> 179.6 | G59: =F59 -> 179.6 | H59: =G59 -> 179.6 | I59: =H59 -> 179.6
B60: Right-of-use assets, net | C60: 173.5 | D60: 202.1 | E60: 303 | F60: =E60+(F81-E81) -> 384.33841 | G60: =F60+(G81-F81) -> 479.03455 | H60: =G60+(H81-G81) -> 571.70615 | I60: =H60+(I81-H81) -> 659.07019
B61: Other | C61: 100.4 | D61: 92 | E61: 60 | F61: =F16*F187 -> 136.05767 | G61: =G16*G187 -> 175.51439 | H61: =H16*H187 -> 214.12756 | I61: =I16*I187 -> 250.52925
B62: Total Other Assets | C62: =SUM(C57:C61) -> 3436.9 | D62: =SUM(D57:D61) -> 3405.6 | E62: =SUM(E57:E61) -> 4471.1 | F62: =SUM(F57:F61) -> 4657.4961 | G62: =SUM(G57:G61) -> 4573.1489 | H62: =SUM(H57:H61) -> 4498.3337 | I62: =SUM(I57:I61) -> 4467.3994
B64: TOTAL ASSETS | C64: =SUM(C62,C51,C54) -> 7998.5 | D64: =SUM(D62,D51,D54) -> 9132.5 | E64: =SUM(E62,E51,E54) -> 12212.4 | F64: =SUM(F62,F51,F54) -> 16460.108 | G64: =SUM(G62,G51,G54) -> 20271.423 | H64: =SUM(H62,H51,H54) -> 24718.754 | I64: =SUM(I62,I51,I54) -> 29835.551
B66: LIABILITIES AND EQUITY:
B68: Liabilities
B69: Current Liabilities
B70: Current portion of long-term debt | C70: 21.8 | D70: 21 | E70: 20.9 | F70: =-F243 -> 20.9 | G70: =-G243 -> 20.9 | H70: =-H243 -> 20.9 | I70: =-I243 -> 20.9
B71: Accounts payable | C71: 986.4 | D71: 1316.4 | E71: 1756.4 | F71: =F261 -> 2528.8089 | G71: =G261 -> 3139.0629 | H71: =H261 -> 3754.5655 | I71: =I261 -> 4304.9847
B72: Deferred revenue | C72: 638.9 | D72: 1063.3 | E72: 1814.7 | F72: =F262 -> 3265.3841 | G72: =G262 -> 3685.8023 | H72: =H262 -> 4068.4237 | I72: =I262 -> 4509.5264
B73: Accrued expenses and other liabilities | C73: 611.8 | D73: 612.6 | E73: 771.6 | F73: =F263 -> 1020.4325 | G73: =G263 -> 1316.358 | H73: =H263 -> 1605.9567 | I73: =I263 -> 1878.9693
B74: Income taxes | C74: 46.5 | D74: 83.7 | E74: 43.4 | F74: =F264 -> 43.4 | G74: =G264 -> 43.4 | H74: =H264 -> 43.4 | I74: =I264 -> 43.4
B75: Total Current liabilities | C75: =SUM(C70:C74) -> 2305.4 | D75: =SUM(D70:D74) -> 3097 | E75: =SUM(E70:E74) -> 4407 | F75: =SUM(F70:F74) -> 6878.9255 | G75: =SUM(G70:G74) -> 8205.5232 | H75: =SUM(H70:H74) -> 9493.2458 | I75: =SUM(I70:I74) -> 10757.781
B77: Non Current Liabilities
B78: Long-term debt, net | C78: 2919.1 | D78: 2907.2 | E78: 2892.1 | F78: =F244+F243 -> 2871.2 | G78: =G244+G243 -> 2850.3 | H78: =H244+H243 -> 2829.4 | I78: =I244+I243 -> 2808.5
B79: Deferred income taxes | C79: 159.5 | D79: 240.3 | E79: 232.8 | F79: =E79 -> 232.8 | G79: =F79 -> 232.8 | H79: =G79 -> 232.8 | I79: =H79 -> 232.8
B80: Warrant Liabilities | C80: 195 | D80: 0 | E80: 0 | F80: =E80 -> 0 | G80: =F80 -> 0 | H80: =G80 -> 0 | I80: =H80 -> 0
B81: Long-term lease liabilities | C81: 142.6 | D81: 171.4 | E81: 245.2 | F81: =F16*F190 -> 326.53841 | G81: =G16*G190 -> 421.23455 | H81: =H16*H190 -> 513.90615 | I81: =I16*I190 -> 601.27019
B82: Other long-term liabilities | C82: 262 | D82: 282.3 | E82: 494 | F82: =E82 -> 494 | G82: =F82 -> 494 | H82: =G82 -> 494 | I82: =H82 -> 494
B83: Total Non Current Liabilities | C83: =SUM(C78:C82) -> 3678.2 | D83: =SUM(D78:D82) -> 3601.2 | E83: =SUM(E78:E82) -> 3864.1 | F83: =SUM(F78:F82) -> 3924.5384 | G83: =SUM(G78:G82) -> 3998.3345 | H83: =SUM(H78:H82) -> 4070.1061 | I83: =SUM(I78:I82) -> 4136.5702
B84: Total Liabilities | C84: =SUM(C83,C75) -> 5983.6 | D84: =SUM(D83,D75) -> 6698.2 | E84: =SUM(E83,E75) -> 8271.1 | F84: =SUM(F83,F75) -> 10803.464 | G84: =SUM(G83,G75) -> 12203.858 | H84: =SUM(H83,H75) -> 13563.352 | I84: =SUM(I83,I75) -> 14894.351
B86: Equity
B87: Additional paid-in capital | C87: 2711.3 | D87: 2821.4 | E87: 2895.2 | F87: =E87 -> 2895.2 | G87: =F87 -> 2895.2 | H87: =G87 -> 2895.2 | I87: =H87 -> 2895.2
B88: Retained earnings | C88: -691.9 | D88: -238.3 | E88: 1027.9 | F88: =E88+F38+F128 -> 2743.2438 | G88: =F88+G38+G128 -> 5154.1652 | H88: =G88+H38+H128 -> 8242.0016 | I88: =H88+I38+I128 -> 12027.8
B89: Accumulated other comprehensive (loss) income | C89: -4.5 | D89: -148.8 | E89: 18.2 | F89: =E89 -> 18.2 | G89: =F89 -> 18.2 | H89: =G89 -> 18.2 | I89: =H89 -> 18.2
B90: Total Equity | C90: =SUM(C87:C89) -> 2014.9 | D90: =SUM(D87:D89) -> 2434.3 | E90: =SUM(E87:E89) -> 3941.3 | F90: =SUM(F87:F89) -> 5656.6438 | G90: =SUM(G87:G89) -> 8067.5652 | H90: =SUM(H87:H89) -> 11155.402 | I90: =SUM(I87:I89) -> 14941.2
B92: TOTAL LIABILITIES & EQUITY | C92: =C90+C84 -> 7998.5 | D92: =D90+D84 -> 9132.5 | E92: =E90+E84 -> 12212.4 | F92: =F90+F84 -> 16460.108 | G92: =G90+G84 -> 20271.423 | H92: =H90+H84 -> 24718.754 | I92: =I90+I84 -> 29835.551
B94: Balance sheet check | C94: =C64-C92 -> 0 | D94: =D64-D92 -> 0 | E94: =E64-E92 -> 0 | F94: =F64-F92 -> 0 | G94: =G64-G92 -> 0 | H94: =H64-H92 -> 0 | I94: =I64-I92 -> 0
B97: CASH FLOW STATEMENT
B100: Cash flows from operating activities
B101: Net income (loss) | C101: =C38 -> 460.2 | D101: =D38 -> 495.8 | E101: =E38 -> 1332.8 | F101: =F38 -> 1805.625 | G101: =G38 -> 2537.812 | H101: =H38 -> 3250.3541 | I101: =I38 -> 3985.0509
B102: Adjustment: (Non Cash/Non Operating Items)
B103: Depreciation | C103: 74.3 | D103: 81.6 | E103: 97.1 | F103: =-F221 -> 138.27 | G103: =-G221 -> 188.95978 | H103: =-H221 -> 239.59729 | I103: =-I221 -> 283.95553
B104: Amortization | C104: 196.7 | D104: 195.4 | E104: 211.5 | F104: =-F234 -> 277.9 | G104: =-G234 -> 218.5 | H104: =-H234 -> 206.1 | I104: =-I234 -> 154.7
B105: Deferred income taxes | C105: -131.6 | D105: -54.5 | E105: 22.6 | F105: 0 | G105: 0 | H105: 0 | I105: 0
B106: Amortization of debt discount and issuance costs | C106: 7.9 | D106: 7 | E106: 5.9 | F106: 0 | G106: 0 | H106: 0 | I106: 0
B107: Change in fair value of warrant liabilities | C107: 157.9 | D107: 449.2 | E107: 0 | F107: 0 | G107: 0 | H107: 0 | I107: 0
B108: Stock-based compensation | C108: 25 | D108: 34.6 | E108: 45.9 | F108: 0 | G108: 0 | H108: 0 | I108: 0
B109: Other | C109: 43.4 | D109: -3.9 | E109: 58.7 | F109: =-(F61-E61) -> -76.05767 | G109: =-(G61-F61) -> -39.456724 | H109: =-(H61-G61) -> -38.613167 | I109: =-(I61-H61) -> -36.401685
B111: Changes in operating working capital | C111: =C148 -> 66.7 | D111: =D148 -> 114.1 | E111: =E148 -> 339.3 | F111: =F148 -> 446.86368 | G111: =G148 -> -400.48296 | H111: =H148 -> -448.1724 | I111: =I148 -> -297.36158
B112: Net cash provided by (used for) operating activities | C112: =SUM(C101:C111) -> 900.5 | D112: =SUM(D101:D111) -> 1319.3 | E112: =SUM(E101:E111) -> 2113.8 | F112: =SUM(F101:F111) -> 2592.601 | G112: =SUM(G101:G111) -> 2505.3321 | H112: =SUM(H101:H111) -> 3209.2658 | I112: =SUM(I101:I111) -> 4089.9432
B114: Cash flows from investing activities
B115: Capital expenditures | C115: -127.9 | D115: -167 | E115: -220 | F115: =-F220 -> -476.20185 | G115: =-G220 -> -526.54318 | H115: =-H220 -> -535.3189 | I115: =-I220 -> -501.05849
B116: Investments in capitalized software | C116: -6.7 | D116: -17.1 | E116: -6.4 | F116: 0 | G116: 0 | H116: 0 | I116: 0
B117: Purchase of short-term investments | C117: 0 | D117: 0 | E117: -539.6 | F117: 0 | G117: 0 | H117: 0 | I117: 0
B118: Proceeds from maturities of short-term investments | C118: 0 | D118: 0 | E118: 450 | F118: 0 | G118: 0 | H118: 0 | I118: 0
B119: Proceeds from disposition of PPE | C119: 12.4 | D119: 0 | E119: 0 | F119: 0 | G119: 0 | H119: 0 | I119: 0
B120: Acquisition of businesses, net of cash acquired | C120: -28.8 | D120: -17.6 | E120: -1184.8 | F120: =-((F238-E238)+F235) -> -306.9 | G120: =-((G238-F238)+G235) -> 0 | H120: =-((H238-G238)+H235) -> 0 | I120: =-((I238-H238)+I235) -> 0
B121: Proceeds from sale of business | C121: 11.9 | D121: 0 | E121: 0 | F121: 0 | G121: 0 | H121: 0 | I121: 0
B122: Net cash provided by (used for) investing activities | C122: =SUM(C115:C121) -> -139.1 | D122: =SUM(D115:D121) -> -201.7 | E122: =SUM(E115:E121) -> -1500.8 | F122: =SUM(F115:F121) -> -783.10185 | G122: =SUM(G115:G121) -> -526.54318 | H122: =SUM(H115:H121) -> -535.3189 | I122: =SUM(I115:I121) -> -501.05849
B124: Cash flows from financing activities
B125: Borrowings from ABL revolving credit facility and short term borrowing | C125: 224.9 | D125: 270 | E125: 0 | F125: 0 | G125: 0 | H125: 0 | I125: 0
B126: Repayments of ABL revolving credit facility and short term borrowing | C126: -459.9 | D126: -270 | E126: 0 | F126: 0 | G126: 0 | H126: 0 | I126: 0
B127: Repayment of long-term debt | C127: -27.1 | D127: -21.1 | E127: -20.9 | F127: =F243 -> -20.9 | G127: =G243 -> -20.9 | H127: =H243 -> -20.9 | I127: =I243 -> -20.9
...

Sheet Assumptions - Detailed
A2: Revenue Growth
A4: 2026 total sales growth: 33% (~$13.6B)
A6: Guidance: In its Q2 2026 release, Vertiv guided full-year net sales of $13.8B to $14.2B (midpoint $14B), which is about 37% total growth over 2025's $10.23B. Organic growth guidance is 30 to 32%; the gap is acquisitions and currency.
A7: Track record: Vertiv has beaten its sales guidance in each of the last two years. For 2025, it guided around $9B at the end of 2024 and delivered $10.23B. This suggests management guides conservatively, which argues for staying close to guidance.
A8: Year to date: H1 2026 sales were $5.92B (Q1 $2.65B, Q2 $3.27B), about 42% of the $14B guidance. In 2025, H1 was about 46% of the full year. If 2026 followed the same seasonal pattern, full-year sales would be around $13B, below guidance. Hitting $14B requires H2 to accelerate meaningfully, with Q4 around $4.3B versus $2.88B in Q4 2025 (roughly 50% growth).
A9: Support for H2 acceleration: Q3 guidance calls for 34 to 36% organic growth, faster than H1. Deferred revenue rose from 9.3% to 17.7% of sales between 2023 and 2025, showing customers are prepaying for future deliveries. Both point to a strong second half.
A10: Historical anchor: 2023–25 sales CAGR was 22%. This reflects the period before the AI buildout was fully underway, so it's used as the long-run level growth fades toward by 2029, not as a check on 2026.
A11: Conclusion: 33% sits between the seasonal estimate (~$13B) and guidance ($14B). It gives credit to Vertiv's track record and H2 visibility, while allowing for the risk that H2 doesn't fully deliver.
A12: Risks: Upside if Vertiv beats guidance again (35 to 38%). Downside if data center capex slows or deliveries slip into 2027 (28 to 30%).
A14: H1 - Gross Profit Margin
B15: 2026 | C15: 2025 | D15: 2024
A16: Net sales | B16: 5923.8 | C16: 4674.1 | D16: 3591.9 | E16: =((B16/D16)^(1/2))-1 -> 0.284216
A17: COGS | B17: 3689.2 | C17: 3091 | D17: 2284.3 | E17: =((B17/D17)^(1/2))-1 -> 0.27083606
A18: GPM | B18: =(B16-B17)/B16 -> 0.37722408 | C18: =(C16-C17)/C16 -> 0.33869622 | D18: =(D16-D17)/D16 -> 0.36404132
A20: PPE SCHEDULE
A21: CAPEX Assumption
A22: Capex H1 2025 | C22: =81.5 -> 81.5
A23: Sales H1 2025 | C23: 4674.1
A24: Capex as % of sales - H1 2025 | C24: =C22/C23 -> 0.017436512
A25: Avg CAPEX (2023-2025) | C25: 0.0203
A26: Pedicted CAPEX in Q2 2026 | C26: 0.04
A28: Depreciation]
A29: H1 2026 DEP | C29: =66.92*2 -> 133.84
A30: H1 2026 PPE | C30: =Model!F219 -> 921.8
A31: H1 dep as % to Opening PPE | C31: =C29/C30 -> 0.14519419
A32: AVG (2023 - 2025) | C32: 0.1505
A34: Goodwill | D34: Additions from acquisitions (Q2 2026)
A35: Goodwill 2025 | B35: 2033.7 | D35: Intangibles 2025 year end | G35: 1894.8
A36: Goodwill 2026 - Q2 | B36: 2283.3 | D36: Intangibles 2026 Q2 | G36: 1800.8
A37: Goodwill acquired | B37: =B36-B35 -> 249.6 | D37: H1 amortization | G37: 151.3
G38: =G36-G35+G37 -> 57.3
A39: Repayments | B39: 20.9
A46: Mandatory repayments of $20.9M a year per the 10-K maturity table; the ~$850M 2028 maturity is assumed to be refinanced
A48: Interest Expense
A57: Total Debt 2025 | B57: 2913 | E57: Debt | F57: Interest (P.a) | G57: Weights
B58: =B57+13.1 -> 2926.1 | D58: Term loan - Floating | E58: 2076.1 | F58: =E58*5.61% -> 116.46921 | G58: =E58/B58 -> 0.70951095 | H58: 0.0561 | I58: =H58*G58 -> 0.039803564
D59: Senior secured noted - Refinanced | E59: 850 | F59: =E59*4.125% -> 35.0625 | G59: =E59/B58 -> 0.29048905 | H59: 0.04125 | I59: =H59*G59 -> 0.011982673
E60: =SUM(E58:E59) -> 2926.1 | F60: =SUM(F58:F59) -> 151.53171 | I60: =SUM(I58:I59) -> 0.051786238
D62: Int Rate | F62: =F60/B57 -> 0.052019125
A63: 2 methods used to verify - Weighted avg and second is int rate calc
A66: Payable days - H1 2026
A67: AP | B67: 2473.1
A68: COGS | B68: 3689.2
B69: =B67/B68*365 -> 244.68218 | C69: =B69/2 -> 122.34109
A71: Dividend Payout Ratio

Sheet Methodology - Each Step
A1: STEP 3: Assumptions
A3: Revenue growth 2026 (33%) – Q2 2026 earnings release – guidance $14B vs H1 seasonality (~$13B), picked in between
A4: Revenue growth 2027 (29%) – Yahoo Finance consensus – used analysts' growth rate, not their dollar figure
A5: Revenue growth 2028 (22%) – Simply Wall St consensus (~21%) – rounded to historical CAGR
A6: Revenue growth 2029 (17%) – own judgment – fade as AI cycle matures
A7: Gross margin (36%) – 10-K + Q2 10-Qs – average of FY 2023–25 and H1 2024–26
A8: SG&A (15% → 13.5%) – own ratios + Morningstar – slower decline than historical trend
A9: Amortization – 10-K intangibles note – copied the estimated future amortization table
A10: Other opex (0.5%) – own ratios – historical average % of sales
A11: Interest – 10-K – held at 2025 level, placeholder until debt schedule
A12: Warrants, debt extinguishment – set to zero – one-offs
A13: Tax rate (23.5%) – own ratios – 2025 rate, only clean year
